docs/conf.py
pyinfoblox2/__init__.py
pyinfoblox2/client.py
pyinfoblox2/errors.py
pyinfoblox2/modules/__init__.py
pyinfoblox2/modules/a_records.py
pyinfoblox2/modules/authzones.py
pyinfoblox2/modules/base.py
pyinfoblox2/modules/cnames.py
pyinfoblox2/modules/containers.py
pyinfoblox2/modules/containersv6.py
pyinfoblox2/modules/delegatedzones.py
pyinfoblox2/modules/dhcp_ranges.py
pyinfoblox2/modules/fixed_addresses.py
pyinfoblox2/modules/forwardzones.py
pyinfoblox2/modules/hosts.py
pyinfoblox2/modules/ipv4addr.py
pyinfoblox2/modules/mac_filters.py
pyinfoblox2/modules/macfilteraddresses.py
pyinfoblox2/modules/misc.py
pyinfoblox2/modules/mx_records.py
pyinfoblox2/modules/nameservers.py
pyinfoblox2/modules/networks.py
pyinfoblox2/modules/networksv6.py
pyinfoblox2/modules/nsgroups.py
pyinfoblox2/modules/ptr_records.py
pyinfoblox2/modules/roaming_hosts.py
pyinfoblox2/modules/scheduled_tasks.py
pyinfoblox2/modules/srv_records.py
pyinfoblox2/modules/txt_records.py
pyinfoblox2-1.0.1.dist-info/licenses/LICENSE
pyinfoblox2-1.0.1.dist-info/METADATA
pyinfoblox2-1.0.1.dist-info/WHEEL
pyinfoblox2-1.0.1.dist-info/top_level.txt
pyinfoblox2-1.0.1.dist-info/RECORD
