Metadata-Version: 2.4
Name: pyinfoblox2
Version: 1.0.1
Summary: Python client for Infoblox WAPI
Author-email: Andy Wilson <andy@shady.org>
Project-URL: Homepage, https://github.com/andy-shady-org/pyinfoblox2
Project-URL: Documentation, https://pyinfoblox2.readthedocs.io/en/latest
Project-URL: Repository, https://github.com/andy-shady-org/pyinfoblox2
Project-URL: Issues, https://github.com/andy-shady-org/pyinfoblox2/issues
Keywords: infoblox,python,pyinfoblox
Classifier: Development Status :: 5 - Production/Stable
Requires-Python: >=3.9
License-File: LICENSE
Requires-Dist: MarkupSafe>=3.0.2
Requires-Dist: httpx>=0.28.1
Requires-Dist: aiofiles>=23.2.1
Requires-Dist: ijson>=3.2.3
Requires-Dist: alive-progress>=3.1.5
Dynamic: license-file
